video_dubbing/__init__.py
video_dubbing/args.py
video_dubbing/asr.py
video_dubbing/ass.py
video_dubbing/cli.py
video_dubbing/executor.py
video_dubbing/ffmpeg.py
video_dubbing/hf_argparser.py
video_dubbing/llm.py
video_dubbing/log.py
video_dubbing/split.py
video_dubbing/srt.py
video_dubbing/translate.py
video_dubbing/tts.py
video_dubbing/types.py
video_dubbing/utils.py
video_dubbing/version.py
video_dubbing/wrapper.py
video_dubbing-1.1.0.dist-info/METADATA
video_dubbing-1.1.0.dist-info/WHEEL
video_dubbing-1.1.0.dist-info/entry_points.txt
video_dubbing-1.1.0.dist-info/licenses/LICENSE
video_dubbing-1.1.0.dist-info/RECORD
