Metadata-Version: 2.4
Name: video-dubbing
Version: 1.1.0
Summary: An AI powered tool to execute end-to-end video dubbing.
Project-URL: github, https://github.com/yuanshanhua/video-dubbing
Author: yuanshanhua
License-Expression: MIT
License-File: LICENSE
Keywords: ai,dubbing,llm,openai,video,whisper
Classifier: License :: OSI Approved :: MIT License
Classifier: Programming Language :: Python :: 3
Requires-Python: ~=3.11
Requires-Dist: aiolimiter>=1.2.1
Requires-Dist: edge-tts>=7.0.0
Requires-Dist: openai>=1.59.9
Requires-Dist: pyyaml
Requires-Dist: rapidfuzz>=3.12.2
Requires-Dist: tomlkit>=0.13.2
Provides-Extra: asr
Requires-Dist: whisperx>=3.3.1; extra == 'asr'
Provides-Extra: npu
Requires-Dist: decorator==5.1.1; extra == 'npu'
Requires-Dist: numpy<2; extra == 'npu'
Requires-Dist: openai-whisper; extra == 'npu'
Requires-Dist: psutil==6.1.1; extra == 'npu'
Requires-Dist: torch-npu==2.4.0; extra == 'npu'
Requires-Dist: torch==2.4.0; extra == 'npu'
Requires-Dist: torchaudio==2.4.0; extra == 'npu'
Requires-Dist: whisperx>=3.3.1; extra == 'npu'
